webdns/__init__.py
webdns/__version__.py
webdns/app.py
webdns/methods.py
webdns/api/__init__.py
webdns/api/api.py
webdns/api/utils.py
webdns-0.0.11.dist-info/METADATA
webdns-0.0.11.dist-info/WHEEL
webdns-0.0.11.dist-info/top_level.txt
webdns-0.0.11.dist-info/RECORD
